axon/__init__.py
axon/_dumper.cpython-37m-darwin.so
axon/_loader.cpython-37m-darwin.so
axon/_objects.cpython-37m-darwin.so
axon/api.py
axon/errors.py
axon/objects.py
axon/odict.cpython-37m-darwin.so
axon/types.py
axon/utils.py
axon/test/__init__.py
axon/test/profiling.py
axon/test/samples.py
axon/test/test_base64.py
axon/test/test_constant.py
axon/test/test_crossref.py
axon/test/test_datetime.py
axon/test/test_decimal.py
axon/test/test_dict.py
axon/test/test_element.py
axon/test/test_errors.py
axon/test/test_float.py
axon/test/test_instance.py
axon/test/test_int.py
axon/test/test_list.py
axon/test/test_load.py
axon/test/test_mapping.py
axon/test/test_odict.py
axon/test/test_samples.py
axon/test/test_sequence.py
axon/test/test_set.py
axon/test/test_string.py
axon/test/test_suite.py
axon/test/test_tuple.py
axon/test/test_unsafe_loads.py
axon/test/benchmark/__init__.py
axon/test/benchmark/test_vs_json.py
axon/test/benchmark/test_vs_yaml.py
pyaxon-0.10.data/scripts/json2axon
pyaxon-0.10.data/scripts/xml2axon
pyaxon-0.10.dist-info/LICENSE.txt
pyaxon-0.10.dist-info/METADATA
pyaxon-0.10.dist-info/WHEEL
pyaxon-0.10.dist-info/top_level.txt
pyaxon-0.10.dist-info/RECORD
